<?xml version="1.0" encoding="utf-8"?>
<arch:spatialUnit xmlns:arch="http://ochre.lib.uchicago.edu/schema/SpatialUnit/SpatialUnit.xsd" xmlns:oc="http://opencontext.org/schema/space_schema_v1.xsd" xmlns:dc="http://purl.org/dc/elements/1.1/" xmlns:gml="http://www.opengis.net/gml" UUID="F402A25B-8C5B-402A-03CD-8ACB421FFBB5" ownedBy="CDD40C27-62ED-4966-AF3D-E781DD0D4846">
  <arch:name>
    <arch:string>Bone 247</arch:string>
  </arch:name>
  <oc:item_class>
    <oc:name>Animal Bone</oc:name>
    <oc:iconURI>http://opencontext.org/database/ui_images/med_oc_icons/animal_bone_50x50.jpg</oc:iconURI>
  </oc:item_class>
  <arch:observations>
    <arch:observation obsNumber="1">
      <oc:obs_metadata>
        <oc:source>z_19_df9d256ed</oc:source>
      </oc:obs_metadata>
      <arch:properties>
        <arch:property>
          <arch:variableID>EA7572FE-9AD4-4A91-23A3-C65023A0A8C8</arch:variableID>
          <arch:valueID>D25C2FB7-C423-43A5-378C-7F0B67B21A6D</arch:valueID>
          <oc:propid href="http://opencontext.org/properties/EDB3D59C-21CA-47E6-65C2-B1848E0BEC21">EDB3D59C-21CA-47E6-65C2-B1848E0BEC21</oc:propid>
          <oc:var_label type="nominal">Date Analyzed</oc:var_label>
          <oc:show_val>2007-04-10</oc:show_val>
        </arch:property>
        <arch:property>
          <arch:variableID>3B4E2A76-10E6-4A20-D50F-FDF953D44032</arch:variableID>
          <arch:valueID>4FB1BF8F-DEA6-4B9A-F0D3-4A369296957D</arch:valueID>
          <oc:propid href="http://opencontext.org/properties/C7FC8426-1654-4632-06C5-82A0C3468273">C7FC8426-1654-4632-06C5-82A0C3468273</oc:propid>
          <oc:var_label type="nominal">Element</oc:var_label>
          <oc:show_val>tibia</oc:show_val>
          <oc:linkedData>
            <oc:relationLink localType="variable" localID="3B4E2A76-10E6-4A20-D50F-FDF953D44032" href="http://opencontext.org/vocabularies/open-context-zooarch/zoo-0079">
              <oc:vocabulary href="http://opencontext.org/vocabularies/open-context-zooarch/">Open Context Zooarchaeology Annotations</oc:vocabulary>
              <oc:label>Has anatomical identification</oc:label>
              <oc:targetLink localType="property" localID="C7FC8426-1654-4632-06C5-82A0C3468273" localURI="http://opencontext.org/properties/C7FC8426-1654-4632-06C5-82A0C3468273" href="http://purl.obolibrary.org/obo/UBERON_0000979">
                <oc:vocabulary href="http://uberon.org">UBERON (Uber Anatomy Ontology)</oc:vocabulary>
                <oc:label>tibia</oc:label>
              </oc:targetLink>
            </oc:relationLink>
          </oc:linkedData>
        </arch:property>
        <arch:property>
          <arch:variableID>70532FCE-5F2A-481A-D1DA-28D93C6F11BC</arch:variableID>
          <arch:valueID>24A780E5-8029-46E2-2D56-BE2BA0613877</arch:valueID>
          <oc:propid href="http://opencontext.org/properties/80CF2F6F-DCD8-483E-7712-7DAC462880E6">80CF2F6F-DCD8-483E-7712-7DAC462880E6</oc:propid>
          <oc:var_label type="nominal">Taxon</oc:var_label>
          <oc:show_val>Ovis sp.</oc:show_val>
          <oc:linkedData>
            <oc:relationLink localType="variable" localID="70532FCE-5F2A-481A-D1DA-28D93C6F11BC" href="http://purl.org/NET/biol/ns#term_hasTaxonomy">
              <oc:vocabulary href="http://purl.org/NET/biol/ns#">Biological Taxonomy Vocabulary</oc:vocabulary>
              <oc:label>Has Biological Taxonomy</oc:label>
              <oc:targetLink localType="property" localID="80CF2F6F-DCD8-483E-7712-7DAC462880E6" localURI="http://opencontext.org/properties/80CF2F6F-DCD8-483E-7712-7DAC462880E6" href="http://eol.org/pages/39510">
                <oc:vocabulary href="http://eol.org/">Encyclopedia of Life</oc:vocabulary>
                <oc:label>Ovis</oc:label>
              </oc:targetLink>
            </oc:relationLink>
          </oc:linkedData>
        </arch:property>
        <arch:property>
          <arch:variableID>3904DD31-EDD2-425E-95CC-E68EDE75CAF7</arch:variableID>
          <arch:valueID>C6587A2D-2565-4BA8-95A9-87F6B5310745</arch:valueID>
          <oc:propid href="http://opencontext.org/properties/A0EC2104-CA7B-4D51-F329-F4986CCFC1AA">A0EC2104-CA7B-4D51-F329-F4986CCFC1AA</oc:propid>
          <oc:var_label type="nominal">Certainty</oc:var_label>
          <oc:show_val>maybe? (c. 66% confidence)</oc:show_val>
        </arch:property>
        <arch:property>
          <arch:variableID>E279FBA5-BDBA-470D-B87F-E5C0504A8F47</arch:variableID>
          <arch:valueID>70AEFB4D-53E0-4978-0D93-C1266F2F9075</arch:valueID>
          <oc:propid href="http://opencontext.org/properties/F01325A4-A9A6-4C1D-9CD7-AD965DEB141A">F01325A4-A9A6-4C1D-9CD7-AD965DEB141A</oc:propid>
          <oc:var_label type="nominal">Skeletal Part</oc:var_label>
          <oc:show_val>distal end</oc:show_val>
        </arch:property>
        <arch:property>
          <arch:variableID>CCF8E4E2-B702-425B-34B4-E683A3DE77C9</arch:variableID>
          <arch:valueID>85FDC240-A0A6-4605-B629-568683793B9E</arch:valueID>
          <oc:propid href="http://opencontext.org/properties/FCD1BE1D-32EC-4313-C064-0E5E85A563DE">FCD1BE1D-32EC-4313-C064-0E5E85A563DE</oc:propid>
          <oc:var_label type="nominal">Fusion Proximal</oc:var_label>
          <oc:show_val>unknown</oc:show_val>
          <oc:linkedData>
            <oc:relationLink localType="variable" localID="CCF8E4E2-B702-425B-34B4-E683A3DE77C9" href="http://opencontext.org/vocabularies/open-context-zooarch/zoo-0077">
              <oc:vocabulary href="http://opencontext.org/vocabularies/open-context-zooarch/">Open Context Zooarchaeology Annotations</oc:vocabulary>
              <oc:label>Has fusion character</oc:label>
            </oc:relationLink>
          </oc:linkedData>
        </arch:property>
        <arch:property>
          <arch:variableID>D2C40312-1D97-450C-2589-B1AA0262B606</arch:variableID>
          <arch:valueID>A6F5D6B1-B62F-424B-A273-F86D929BD4E2</arch:valueID>
          <oc:propid href="http://opencontext.org/properties/95A78C11-6FA6-465D-0A20-BB55F0A24BF5">95A78C11-6FA6-465D-0A20-BB55F0A24BF5</oc:propid>
          <oc:var_label type="nominal">Fusion Distal</oc:var_label>
          <oc:show_val>fused</oc:show_val>
          <oc:linkedData>
            <oc:relationLink localType="variable" localID="D2C40312-1D97-450C-2589-B1AA0262B606" href="http://opencontext.org/vocabularies/open-context-zooarch/zoo-0077">
              <oc:vocabulary href="http://opencontext.org/vocabularies/open-context-zooarch/">Open Context Zooarchaeology Annotations</oc:vocabulary>
              <oc:label>Has fusion character</oc:label>
              <oc:targetLink localType="property" localID="95A78C11-6FA6-465D-0A20-BB55F0A24BF5" localURI="http://opencontext.org/properties/95A78C11-6FA6-465D-0A20-BB55F0A24BF5" href="http://opencontext.org/vocabularies/open-context-zooarch/zoo-0057">
                <oc:vocabulary href="http://opencontext.org/vocabularies/open-context-zooarch/">Open Context Zooarchaeology Annotations</oc:vocabulary>
                <oc:label>Distal epiphysis fused</oc:label>
              </oc:targetLink>
            </oc:relationLink>
          </oc:linkedData>
        </arch:property>
        <arch:property>
          <arch:variableID>10175AD5-44E4-4D5F-1140-7A9ADAAE0FBE</arch:variableID>
          <arch:integer href="http://www.freebase.com/view/en/counting_measure" name="counting measure" abrv="count">1</arch:integer>
          <oc:propid href="http://opencontext.org/properties/EA0A5D05-4F77-48FF-893E-47E69A549D16">EA0A5D05-4F77-48FF-893E-47E69A549D16</oc:propid>
          <oc:var_label type="integer">Count (# Elements Present)</oc:var_label>
          <oc:show_val>1</oc:show_val>
        </arch:property>
        <arch:property>
          <arch:variableID>E0A558CC-2B7F-467F-3035-1D5097C1315D</arch:variableID>
          <arch:valueID>1F1DDC98-CAB5-4019-2064-8786161C36A2</arch:valueID>
          <oc:propid href="http://opencontext.org/properties/D46C62F6-2E5E-4393-ECFC-2A49EF3E02F7">D46C62F6-2E5E-4393-ECFC-2A49EF3E02F7</oc:propid>
          <oc:var_label type="nominal">Diagnostic Zones</oc:var_label>
          <oc:show_val>one diagnostic zone present</oc:show_val>
        </arch:property>
        <arch:property>
          <arch:variableID>C9196C38-230E-48BC-5FB0-263E7D34CACA</arch:variableID>
          <oc:annotations about="C9196C38-230E-48BC-5FB0-263E7D34CACA" aboutType="variable">
            <oc:annotation>
              <oc:relationLink type="Measurement type"/>
              <oc:targetLink href="http://opencontext.org/vocabularies/open-context-zooarch/zoo-0017" name="Dd" abrv="">
                <oc:vocabulary href="http://opencontext.org/vocabularies/open-context-zooarch/">Open Context Zooarchaeology Annotations</oc:vocabulary>
              </oc:targetLink>
            </oc:annotation>
          </oc:annotations>
          <arch:decimal href="http://www.freebase.com/view/en/millimeter" name="millimeter" abrv="mm">22.7</arch:decimal>
          <oc:propid href="http://opencontext.org/properties/52D0ECDE-71C6-4D9E-6BD7-D844A6852EA0">52D0ECDE-71C6-4D9E-6BD7-D844A6852EA0</oc:propid>
          <oc:var_label type="decimal">Dd</oc:var_label>
          <oc:show_val>22.7</oc:show_val>
        </arch:property>
        <arch:property>
          <arch:variableID>D14021F5-C9AB-4C2F-3199-590BDF8D8441</arch:variableID>
          <oc:annotations about="D14021F5-C9AB-4C2F-3199-590BDF8D8441" aboutType="variable">
            <oc:annotation>
              <oc:relationLink type="Measurement type"/>
              <oc:targetLink href="http://opencontext.org/vocabularies/open-context-zooarch/zoo-0009" name="Bd" abrv="">
                <oc:vocabulary href="http://opencontext.org/vocabularies/open-context-zooarch/">Open Context Zooarchaeology Annotations</oc:vocabulary>
              </oc:targetLink>
            </oc:annotation>
          </oc:annotations>
          <arch:decimal href="http://www.freebase.com/view/en/millimeter" name="millimeter" abrv="mm">29.3</arch:decimal>
          <oc:propid href="http://opencontext.org/properties/C6AE6E5A-E618-40A6-ABB8-2B7BF7A1DA4F">C6AE6E5A-E618-40A6-ABB8-2B7BF7A1DA4F</oc:propid>
          <oc:var_label type="decimal">Bd</oc:var_label>
          <oc:show_val>29.3</oc:show_val>
        </arch:property>
      </arch:properties>
      <arch:links>
        <arch:docID type="person" info="Principle Author / Analyst">8CFA04D7-F9F2-4336-6B14-0057FCB6D97F</arch:docID>
        <oc:person_links>
          <oc:link href="http://opencontext.org/persons/8CFA04D7-F9F2-4336-6B14-0057FCB6D97F" cite="contributor">
            <oc:name>Benjamin S. Arbuckle</oc:name>
            <oc:id>8CFA04D7-F9F2-4336-6B14-0057FCB6D97F</oc:id>
            <oc:relation>Principle Author / Analyst</oc:relation>
          </oc:link>
        </oc:person_links>
      </arch:links>
    </arch:observation>
  </arch:observations>
  <oc:context>
    <oc:tree id="default">
      <oc:parent href="http://opencontext.org/subjects/1_Global_Spatial">
        <oc:name>Turkey</oc:name>
        <oc:id>1_Global_Spatial</oc:id>
        <oc:level>3</oc:level>
        <oc:item_class>
          <oc:name>Region</oc:name>
          <oc:iconURI>http://opencontext.org/database/ui_images/med_oc_icons/region_30x30.jpg</oc:iconURI>
        </oc:item_class>
      </oc:parent>
      <oc:parent href="http://opencontext.org/subjects/B59AC3A1-501B-4E86-D143-35275D10C498">
        <oc:name>Suberde</oc:name>
        <oc:id>B59AC3A1-501B-4E86-D143-35275D10C498</oc:id>
        <oc:level>2</oc:level>
        <oc:item_class>
          <oc:name>Site</oc:name>
          <oc:iconURI>http://opencontext.org/database/ui_images/med_oc_icons/site_30x30.jpg</oc:iconURI>
        </oc:item_class>
      </oc:parent>
      <oc:parent href="http://opencontext.org/subjects/D3A8C5B6-277A-4B5E-29D0-3D8E41F4A486">
        <oc:name>Bag  Not recorded</oc:name>
        <oc:id>D3A8C5B6-277A-4B5E-29D0-3D8E41F4A486</oc:id>
        <oc:level>1</oc:level>
        <oc:item_class>
          <oc:name>Sample</oc:name>
          <oc:iconURI>http://opencontext.org/database/ui_images/med_oc_icons/sample_30x30.jpg</oc:iconURI>
        </oc:item_class>
      </oc:parent>
    </oc:tree>
  </oc:context>
  <oc:metadata>
    <dc:title>Erbaba Höyük and Suberde Zooarchaeology: Bone 247 (Animal Bone)</dc:title>
    <dc:publisher>Open Context</dc:publisher>
    <dc:date>2013-05-17</dc:date>
    <dc:subject>Zooarchaeology</dc:subject>
    <dc:subject>Turkey</dc:subject>
    <dc:subject>Village</dc:subject>
    <dc:subject>Neolithic</dc:subject>
    <dc:subject>Mammal remains</dc:subject>
    <dc:subject>Jacques Bordaz</dc:subject>
    <dc:subject>Faunal Data</dc:subject>
    <dc:subject>Central Anatolia</dc:subject>
    <dc:subject>Animal Domestication</dc:subject>
    <dc:contributor href="http://opencontext.org/persons/8CFA04D7-F9F2-4336-6B14-0057FCB6D97F">Benjamin S. Arbuckle</dc:contributor>
    <dc:creator href="http://opencontext.org/persons/8CFA04D7-F9F2-4336-6B14-0057FCB6D97F">Benjamin S. Arbuckle</dc:creator>
    <dc:identifier>http://opencontext.org/subjects/F402A25B-8C5B-402A-03CD-8ACB421FFBB5</dc:identifier>
    <oc:project_name href="http://opencontext.org/projects/CDD40C27-62ED-4966-AF3D-E781DD0D4846">Erbaba Höyük and Suberde Zooarchaeology</oc:project_name>
    <oc:pub_date>2013-05-17T00:00:00-07:00</oc:pub_date>
    <oc:coins>ctx_ver=Z39.88-2004&amp;rft_val_fmt=info%3Aofi%2Ffmt%3Akev%3Amtx%3Adc&amp;rft_val_fmt=info%3Aofi%2Ffmt%3Akev%3Amtx%3Adc&amp;rft.type=dataset&amp;rft.title=Erbaba+H%C3%B6y%C3%BCk+and+Suberde+Zooarchaeology%3A+Bone+247+%28Animal+Bone%29&amp;rft.publisher=Open+Context&amp;rft.source=Open+Context&amp;rft.subject=Zooarchaeology&amp;rft.subject=Turkey&amp;rft.subject=Village&amp;rft.subject=Neolithic&amp;rft.subject=Mammal+remains&amp;rft.subject=Jacques+Bordaz&amp;rft.subject=Faunal+Data&amp;rft.subject=Central+Anatolia&amp;rft.subject=Animal+Domestication&amp;rft.contributor=Benjamin+S.+Arbuckle&amp;rft.creator=Benjamin+S.+Arbuckle&amp;rft.identifier=http%3A%2F%2Fopencontext.org%2Fsubjects%2FF402A25B-8C5B-402A-03CD-8ACB421FFBB5</oc:coins>
    <oc:geo_reference>
      <oc:geo_lat>37.35</oc:geo_lat>
      <oc:geo_long>31.933333</oc:geo_long>
      <oc:metasource ref_type="contained" href="http://opencontext.org/subjects/B59AC3A1-501B-4E86-D143-35275D10C498">
        <oc:source_name>Suberde</oc:source_name>
        <oc:source_id>B59AC3A1-501B-4E86-D143-35275D10C498</oc:source_id>
      </oc:metasource>
    </oc:geo_reference>
    <oc:copyright_lic href="http://creativecommons.org/licenses/by/3.0/">
      <oc:lic_name>Attribution</oc:lic_name>
      <oc:lic_vers>3</oc:lic_vers>
      <oc:lic_URI>http://creativecommons.org/licenses/by/3.0/</oc:lic_URI>
      <oc:lic_icon_URI>http://i.creativecommons.org/l/by/3.0/88x31.png</oc:lic_icon_URI>
    </oc:copyright_lic>
  </oc:metadata>
  <oc:social_usage>
    <oc:last_updated>2013-05-23T20:33:18-07:00</oc:last_updated>
    <oc:item_views>
      <oc:count>1</oc:count>
      <oc:view_time>2013/05/23 20:33:18</oc:view_time>
    </oc:item_views>
    <oc:user_tags>
      <oc:tag type="chronological" status="public">
        <oc:name>(7,500 BCE - 7,000 BCE)</oc:name>
        <oc:chrono isDuration="true">
          <oc:time_start>-7500</oc:time_start>
          <oc:time_finish>-7000</oc:time_finish>
          <oc:metasource ref_type="contained" href="http://opencontext.org/subjects/B59AC3A1-501B-4E86-D143-35275D10C498">
            <oc:source_name>Suberde</oc:source_name>
            <oc:source_id>B59AC3A1-501B-4E86-D143-35275D10C498</oc:source_id>
          </oc:metasource>
        </oc:chrono>
        <oc:tag_creator id="oc">
          <oc:creator_name>Open Context Editors</oc:creator_name>
          <oc:set_label>Default set</oc:set_label>
          <oc:set_id>Default set</oc:set_id>
          <oc:set_date>2013-02-28T14:14:51-07:00</oc:set_date>
        </oc:tag_creator>
      </oc:tag>
    </oc:user_tags>
  </oc:social_usage>
</arch:spatialUnit>
